<annotation>
	<folder>train</folder>
	<filename>20211222_112411.jpg</filename>
	<path>C:\PKL\SAM-AI\TensorFlow\workspace\images\train\20211222_112411.jpg</path>
	<source>
		<database>Unknown</database>
	</source>
	<size>
		<width>1800</width>
		<height>4000</height>
		<depth>3</depth>
	</size>
	<segmented>0</segmented>
	<object>
		<name>90101225202100</name>
		<pose>Unspecified</pose>
		<truncated>0</truncated>
		<difficult>0</difficult>
		<bndbox>
			<xmin>179</xmin>
			<ymin>1389</ymin>
			<xmax>477</xmax>
			<ymax>1563</ymax>
		</bndbox>
	</object>
	<object>
		<name>90101225212100</name>
		<pose>Unspecified</pose>
		<truncated>0</truncated>
		<difficult>0</difficult>
		<bndbox>
			<xmin>800</xmin>
			<ymin>1558</ymin>
			<xmax>1049</xmax>
			<ymax>1725</ymax>
		</bndbox>
	</object>
	<object>
		<name>90101225226101</name>
		<pose>Unspecified</pose>
		<truncated>0</truncated>
		<difficult>0</difficult>
		<bndbox>
			<xmin>1409</xmin>
			<ymin>1361</ymin>
			<xmax>1705</xmax>
			<ymax>1547</ymax>
		</bndbox>
	</object>
	<object>
		<name>90101225202101</name>
		<pose>Unspecified</pose>
		<truncated>0</truncated>
		<difficult>0</difficult>
		<bndbox>
			<xmin>291</xmin>
			<ymin>1870</ymin>
			<xmax>588</xmax>
			<ymax>2049</ymax>
		</bndbox>
	</object>
	<object>
		<name>90101225218101</name>
		<pose>Unspecified</pose>
		<truncated>0</truncated>
		<difficult>0</difficult>
		<bndbox>
			<xmin>599</xmin>
			<ymin>2044</ymin>
			<xmax>885</xmax>
			<ymax>2206</ymax>
		</bndbox>
	</object>
	<object>
		<name>90101225209100</name>
		<pose>Unspecified</pose>
		<truncated>0</truncated>
		<difficult>0</difficult>
		<bndbox>
			<xmin>1472</xmin>
			<ymin>1856</ymin>
			<xmax>1711</xmax>
			<ymax>2028</ymax>
		</bndbox>
	</object>
</annotation>
