<annotation>
	<folder>train</folder>
	<filename>20211222_112411_rotated180.jpg</filename>
	<path>C:\PKL\SAM-AI\TensorFlow\workspace\images\train\20211222_112411_rotated180.jpg</path>
	<source>
		<database>Unknown</database>
	</source>
	<size>
		<width>1800</width>
		<height>4000</height>
		<depth>3</depth>
	</size>
	<segmented>0</segmented>
	<object>
		<name>FantasticRiceCrackersSeaweed</name>
		<pose>Unspecified</pose>
		<truncated>0</truncated>
		<difficult>0</difficult>
		<bndbox>
			<xmin>962</xmin>
			<ymin>3215</ymin>
			<xmax>1494</xmax>
			<ymax>3417</ymax>
		</bndbox>
	</object>
	<object>
		<name>FantasticRiceCrackersSeaweed</name>
		<pose>Unspecified</pose>
		<truncated>0</truncated>
		<difficult>0</difficult>
		<bndbox>
			<xmin>982</xmin>
			<ymin>3422</ymin>
			<xmax>1507</xmax>
			<ymax>3626</ymax>
		</bndbox>
	</object>
	<object>
		<name>FantasticRiceCrackersCheese</name>
		<pose>Unspecified</pose>
		<truncated>0</truncated>
		<difficult>0</difficult>
		<bndbox>
			<xmin>434</xmin>
			<ymin>3219</ymin>
			<xmax>962</xmax>
			<ymax>3417</ymax>
		</bndbox>
	</object>
	<object>
		<name>FantasticRiceCrackersCheese</name>
		<pose>Unspecified</pose>
		<truncated>0</truncated>
		<difficult>0</difficult>
		<bndbox>
			<xmin>455</xmin>
			<ymin>3430</ymin>
			<xmax>973</xmax>
			<ymax>3617</ymax>
		</bndbox>
	</object>
	<object>
		<name>FantasticRiceCrackersHoney&amp;Soy</name>
		<pose>Unspecified</pose>
		<truncated>1</truncated>
		<difficult>0</difficult>
		<bndbox>
			<xmin>1</xmin>
			<ymin>3230</ymin>
			<xmax>432</xmax>
			<ymax>3432</ymax>
		</bndbox>
	</object>
	<object>
		<name>FantasticRiceCrackersHoney&amp;Soy</name>
		<pose>Unspecified</pose>
		<truncated>1</truncated>
		<difficult>0</difficult>
		<bndbox>
			<xmin>1</xmin>
			<ymin>3639</ymin>
			<xmax>464</xmax>
			<ymax>3823</ymax>
		</bndbox>
	</object>
	<object>
		<name>FantasticRiceCrackersHoney&amp;Soy</name>
		<pose>Unspecified</pose>
		<truncated>1</truncated>
		<difficult>0</difficult>
		<bndbox>
			<xmin>1</xmin>
			<ymin>3436</ymin>
			<xmax>443</xmax>
			<ymax>3636</ymax>
		</bndbox>
	</object>
	<object>
		<name>SquarePuffBiskuit</name>
		<pose>Unspecified</pose>
		<truncated>1</truncated>
		<difficult>0</difficult>
		<bndbox>
			<xmin>1</xmin>
			<ymin>2726</ymin>
			<xmax>237</xmax>
			<ymax>3036</ymax>
		</bndbox>
	</object>
	<object>
		<name>SquarePuffBiskuit</name>
		<pose>Unspecified</pose>
		<truncated>0</truncated>
		<difficult>0</difficult>
		<bndbox>
			<xmin>262</xmin>
			<ymin>2718</ymin>
			<xmax>556</xmax>
			<ymax>3045</ymax>
		</bndbox>
	</object>
	<object>
		<name>HatariMalkist</name>
		<pose>Unspecified</pose>
		<truncated>0</truncated>
		<difficult>0</difficult>
		<bndbox>
			<xmin>564</xmin>
			<ymin>2706</ymin>
			<xmax>796</xmax>
			<ymax>3004</ymax>
		</bndbox>
	</object>
	<object>
		<name>KlopSalutoChocoNutCaramel</name>
		<pose>Unspecified</pose>
		<truncated>0</truncated>
		<difficult>0</difficult>
		<bndbox>
			<xmin>830</xmin>
			<ymin>2706</ymin>
			<xmax>1111</xmax>
			<ymax>2857</ymax>
		</bndbox>
	</object>
	<object>
		<name>SiantarTopDeoGoPotato</name>
		<pose>Unspecified</pose>
		<truncated>0</truncated>
		<difficult>0</difficult>
		<bndbox>
			<xmin>1126</xmin>
			<ymin>2694</ymin>
			<xmax>1624</xmax>
			<ymax>2874</ymax>
		</bndbox>
	</object>
	<object>
		<name>90101225202100</name>
		<pose>Unspecified</pose>
		<truncated>0</truncated>
		<difficult>0</difficult>
		<bndbox>
			<xmin>1322</xmin>
			<ymin>2440</ymin>
			<xmax>1620</xmax>
			<ymax>2606</ymax>
		</bndbox>
	</object>
	<object>
		<name>90101225202100</name>
		<pose>Unspecified</pose>
		<truncated>0</truncated>
		<difficult>0</difficult>
		<bndbox>
			<xmin>1307</xmin>
			<ymin>2260</ymin>
			<xmax>1605</xmax>
			<ymax>2434</ymax>
		</bndbox>
	</object>
	<object>
		<name>90101225202100</name>
		<pose>Unspecified</pose>
		<truncated>0</truncated>
		<difficult>0</difficult>
		<bndbox>
			<xmin>1013</xmin>
			<ymin>2257</ymin>
			<xmax>1307</xmax>
			<ymax>2438</ymax>
		</bndbox>
	</object>
	<object>
		<name>90101225202100</name>
		<pose>Unspecified</pose>
		<truncated>0</truncated>
		<difficult>0</difficult>
		<bndbox>
			<xmin>1015</xmin>
			<ymin>2434</ymin>
			<xmax>1313</xmax>
			<ymax>2626</ymax>
		</bndbox>
	</object>
	<object>
		<name>90101225212100</name>
		<pose>Unspecified</pose>
		<truncated>0</truncated>
		<difficult>0</difficult>
		<bndbox>
			<xmin>747</xmin>
			<ymin>2274</ymin>
			<xmax>992</xmax>
			<ymax>2443</ymax>
		</bndbox>
	</object>
	<object>
		<name>90101225212100</name>
		<pose>Unspecified</pose>
		<truncated>0</truncated>
		<difficult>0</difficult>
		<bndbox>
			<xmin>762</xmin>
			<ymin>2451</ymin>
			<xmax>1007</xmax>
			<ymax>2620</ymax>
		</bndbox>
	</object>
	<object>
		<name>90101225212100</name>
		<pose>Unspecified</pose>
		<truncated>0</truncated>
		<difficult>0</difficult>
		<bndbox>
			<xmin>462</xmin>
			<ymin>2288</ymin>
			<xmax>707</xmax>
			<ymax>2457</ymax>
		</bndbox>
	</object>
	<object>
		<name>90101225226101</name>
		<pose>Unspecified</pose>
		<truncated>0</truncated>
		<difficult>0</difficult>
		<bndbox>
			<xmin>100</xmin>
			<ymin>2283</ymin>
			<xmax>375</xmax>
			<ymax>2445</ymax>
		</bndbox>
	</object>
	<object>
		<name>90101225226101</name>
		<pose>Unspecified</pose>
		<truncated>0</truncated>
		<difficult>0</difficult>
		<bndbox>
			<xmin>92</xmin>
			<ymin>2447</ymin>
			<xmax>392</xmax>
			<ymax>2636</ymax>
		</bndbox>
	</object>
	<object>
		<name>90101225209100</name>
		<pose>Unspecified</pose>
		<truncated>0</truncated>
		<difficult>0</difficult>
		<bndbox>
			<xmin>71</xmin>
			<ymin>1815</ymin>
			<xmax>307</xmax>
			<ymax>1966</ymax>
		</bndbox>
	</object>
	<object>
		<name>90101225209100</name>
		<pose>Unspecified</pose>
		<truncated>0</truncated>
		<difficult>0</difficult>
		<bndbox>
			<xmin>96</xmin>
			<ymin>1973</ymin>
			<xmax>322</xmax>
			<ymax>2136</ymax>
		</bndbox>
	</object>
	<object>
		<name>90101225209100</name>
		<pose>Unspecified</pose>
		<truncated>0</truncated>
		<difficult>0</difficult>
		<bndbox>
			<xmin>339</xmin>
			<ymin>1808</ymin>
			<xmax>566</xmax>
			<ymax>1952</ymax>
		</bndbox>
	</object>
	<object>
		<name>90101225218101</name>
		<pose>Unspecified</pose>
		<truncated>0</truncated>
		<difficult>0</difficult>
		<bndbox>
			<xmin>617</xmin>
			<ymin>1802</ymin>
			<xmax>905</xmax>
			<ymax>1957</ymax>
		</bndbox>
	</object>
	<object>
		<name>90101225218101</name>
		<pose>Unspecified</pose>
		<truncated>0</truncated>
		<difficult>0</difficult>
		<bndbox>
			<xmin>924</xmin>
			<ymin>1798</ymin>
			<xmax>1203</xmax>
			<ymax>1955</ymax>
		</bndbox>
	</object>
	<object>
		<name>90101225218101</name>
		<pose>Unspecified</pose>
		<truncated>0</truncated>
		<difficult>0</difficult>
		<bndbox>
			<xmin>909</xmin>
			<ymin>1960</ymin>
			<xmax>1192</xmax>
			<ymax>2096</ymax>
		</bndbox>
	</object>
	<object>
		<name>90101225202101</name>
		<pose>Unspecified</pose>
		<truncated>0</truncated>
		<difficult>0</difficult>
		<bndbox>
			<xmin>1213</xmin>
			<ymin>1794</ymin>
			<xmax>1496</xmax>
			<ymax>1949</ymax>
		</bndbox>
	</object>
	<object>
		<name>90101225202101</name>
		<pose>Unspecified</pose>
		<truncated>0</truncated>
		<difficult>0</difficult>
		<bndbox>
			<xmin>1227</xmin>
			<ymin>1956</ymin>
			<xmax>1500</xmax>
			<ymax>2126</ymax>
		</bndbox>
	</object>
	<object>
		<name>90101225202101</name>
		<pose>Unspecified</pose>
		<truncated>1</truncated>
		<difficult>0</difficult>
		<bndbox>
			<xmin>1530</xmin>
			<ymin>1790</ymin>
			<xmax>1800</xmax>
			<ymax>1938</ymax>
		</bndbox>
	</object>
	<object>
		<name>KokolaMalkistSusu</name>
		<pose>Unspecified</pose>
		<truncated>0</truncated>
		<difficult>0</difficult>
		<bndbox>
			<xmin>402</xmin>
			<ymin>1411</ymin>
			<xmax>630</xmax>
			<ymax>1655</ymax>
		</bndbox>
	</object>
	<object>
		<name>KhongGuanMalkistCokelat</name>
		<pose>Unspecified</pose>
		<truncated>0</truncated>
		<difficult>0</difficult>
		<bndbox>
			<xmin>635</xmin>
			<ymin>1292</ymin>
			<xmax>883</xmax>
			<ymax>1413</ymax>
		</bndbox>
	</object>
	<object>
		<name>KhongGuanMalkistCokelat</name>
		<pose>Unspecified</pose>
		<truncated>0</truncated>
		<difficult>0</difficult>
		<bndbox>
			<xmin>917</xmin>
			<ymin>1296</ymin>
			<xmax>1162</xmax>
			<ymax>1409</ymax>
		</bndbox>
	</object>
	<object>
		<name>KhongGuanMalkistCokelat</name>
		<pose>Unspecified</pose>
		<truncated>0</truncated>
		<difficult>0</difficult>
		<bndbox>
			<xmin>920</xmin>
			<ymin>1419</ymin>
			<xmax>1168</xmax>
			<ymax>1541</ymax>
		</bndbox>
	</object>
	<object>
		<name>KhongGuanMalkistCokelat</name>
		<pose>Unspecified</pose>
		<truncated>0</truncated>
		<difficult>0</difficult>
		<bndbox>
			<xmin>634</xmin>
			<ymin>1428</ymin>
			<xmax>892</xmax>
			<ymax>1547</ymax>
		</bndbox>
	</object>
	<object>
		<name>KhongGuanMalkistCokelat</name>
		<pose>Unspecified</pose>
		<truncated>0</truncated>
		<difficult>0</difficult>
		<bndbox>
			<xmin>925</xmin>
			<ymin>1552</ymin>
			<xmax>1181</xmax>
			<ymax>1690</ymax>
		</bndbox>
	</object>
	<object>
		<name>KhongGuanMalkistCokelat</name>
		<pose>Unspecified</pose>
		<truncated>0</truncated>
		<difficult>0</difficult>
		<bndbox>
			<xmin>645</xmin>
			<ymin>1568</ymin>
			<xmax>900</xmax>
			<ymax>1691</ymax>
		</bndbox>
	</object>
	<object>
		<name>NissinGoldenMalkist</name>
		<pose>Unspecified</pose>
		<truncated>0</truncated>
		<difficult>0</difficult>
		<bndbox>
			<xmin>1224</xmin>
			<ymin>1507</ymin>
			<xmax>1512</xmax>
			<ymax>1627</ymax>
		</bndbox>
	</object>
	<object>
		<name>NissinGoldenMalkist</name>
		<pose>Unspecified</pose>
		<truncated>1</truncated>
		<difficult>0</difficult>
		<bndbox>
			<xmin>1522</xmin>
			<ymin>1396</ymin>
			<xmax>1800</xmax>
			<ymax>1510</ymax>
		</bndbox>
	</object>
	<object>
		<name>NissinGoldenMalkist</name>
		<pose>Unspecified</pose>
		<truncated>0</truncated>
		<difficult>0</difficult>
		<bndbox>
			<xmin>1520</xmin>
			<ymin>1394</ymin>
			<xmax>1798</xmax>
			<ymax>1508</ymax>
		</bndbox>
	</object>
	<object>
		<name>NissinGoldenMalkist</name>
		<pose>Unspecified</pose>
		<truncated>1</truncated>
		<difficult>0</difficult>
		<bndbox>
			<xmin>1540</xmin>
			<ymin>1271</ymin>
			<xmax>1800</xmax>
			<ymax>1388</ymax>
		</bndbox>
	</object>
	<object>
		<name>NissinGoldenMalkist</name>
		<pose>Unspecified</pose>
		<truncated>0</truncated>
		<difficult>0</difficult>
		<bndbox>
			<xmin>1215</xmin>
			<ymin>1277</ymin>
			<xmax>1484</xmax>
			<ymax>1388</ymax>
		</bndbox>
	</object>
	<object>
		<name>NissinGoldenMalkist</name>
		<pose>Unspecified</pose>
		<truncated>0</truncated>
		<difficult>0</difficult>
		<bndbox>
			<xmin>1206</xmin>
			<ymin>1395</ymin>
			<xmax>1482</xmax>
			<ymax>1506</ymax>
		</bndbox>
	</object>
	<object>
		<name>KhongGuanSaltinesVegetablesCrackers</name>
		<pose>Unspecified</pose>
		<truncated>0</truncated>
		<difficult>0</difficult>
		<bndbox>
			<xmin>633</xmin>
			<ymin>873</ymin>
			<xmax>894</xmax>
			<ymax>1115</ymax>
		</bndbox>
	</object>
	<object>
		<name>NissinVegeeBiscuits</name>
		<pose>Unspecified</pose>
		<truncated>0</truncated>
		<difficult>0</difficult>
		<bndbox>
			<xmin>919</xmin>
			<ymin>866</ymin>
			<xmax>1228</xmax>
			<ymax>981</ymax>
		</bndbox>
	</object>
	<object>
		<name>NissinVegeeBiscuits</name>
		<pose>Unspecified</pose>
		<truncated>0</truncated>
		<difficult>0</difficult>
		<bndbox>
			<xmin>915</xmin>
			<ymin>980</ymin>
			<xmax>1228</xmax>
			<ymax>1128</ymax>
		</bndbox>
	</object>
	<object>
		<name>NissinVegetableCrackers</name>
		<pose>Unspecified</pose>
		<truncated>0</truncated>
		<difficult>0</difficult>
		<bndbox>
			<xmin>1257</xmin>
			<ymin>823</ymin>
			<xmax>1507</xmax>
			<ymax>951</ymax>
		</bndbox>
	</object>
	<object>
		<name>NissinVegetableCrackers</name>
		<pose>Unspecified</pose>
		<truncated>0</truncated>
		<difficult>0</difficult>
		<bndbox>
			<xmin>1264</xmin>
			<ymin>1030</ymin>
			<xmax>1497</xmax>
			<ymax>1158</ymax>
		</bndbox>
	</object>
	<object>
		<name>NissinVegetableCrackers</name>
		<pose>Unspecified</pose>
		<truncated>0</truncated>
		<difficult>0</difficult>
		<bndbox>
			<xmin>1518</xmin>
			<ymin>860</ymin>
			<xmax>1747</xmax>
			<ymax>990</ymax>
		</bndbox>
	</object>
	<object>
		<name>NissinVegetableCrackers</name>
		<pose>Unspecified</pose>
		<truncated>0</truncated>
		<difficult>0</difficult>
		<bndbox>
			<xmin>1519</xmin>
			<ymin>984</ymin>
			<xmax>1766</xmax>
			<ymax>1130</ymax>
		</bndbox>
	</object>
	<object>
		<name>KhongGuanCocoaPuffBiskuitWafer</name>
		<pose>Unspecified</pose>
		<truncated>0</truncated>
		<difficult>0</difficult>
		<bndbox>
			<xmin>1406</xmin>
			<ymin>352</ymin>
			<xmax>1669</xmax>
			<ymax>778</ymax>
		</bndbox>
	</object>
	<object>
		<name>KhongGuanCocoaPuffBiskuitWafer</name>
		<pose>Unspecified</pose>
		<truncated>0</truncated>
		<difficult>0</difficult>
		<bndbox>
			<xmin>1113</xmin>
			<ymin>378</ymin>
			<xmax>1391</xmax>
			<ymax>788</ymax>
		</bndbox>
	</object>
	<object>
		<name>NarayaCheeseCorn</name>
		<pose>Unspecified</pose>
		<truncated>0</truncated>
		<difficult>0</difficult>
		<bndbox>
			<xmin>449</xmin>
			<ymin>343</ymin>
			<xmax>781</xmax>
			<ymax>799</ymax>
		</bndbox>
	</object>
	<object>
		<name>NarayaCheeseCorn</name>
		<pose>Unspecified</pose>
		<truncated>0</truncated>
		<difficult>0</difficult>
		<bndbox>
			<xmin>803</xmin>
			<ymin>413</ymin>
			<xmax>1104</xmax>
			<ymax>788</ymax>
		</bndbox>
	</object>
</annotation>
